vkit/__init__.py
vkit/element/__init__.py
vkit/element/box.py
vkit/element/image.py
vkit/element/lexicon.py
vkit/element/line.py
vkit/element/mask.py
vkit/element/opt.py
vkit/element/point.py
vkit/element/polygon.py
vkit/element/score_map.py
vkit/element/type.py
vkit/element/uniqueness.py
vkit/engine/__init__.py
vkit/engine/interface.py
vkit/engine/barcode/__init__.py
vkit/engine/barcode/code39.py
vkit/engine/barcode/qr.py
vkit/engine/barcode/type.py
vkit/engine/char_and_font_sampler/__init__.py
vkit/engine/char_heatmap/__init__.py
vkit/engine/char_heatmap/default.py
vkit/engine/char_heatmap/type.py
vkit/engine/char_sampler/__init__.py
vkit/engine/char_sampler/corpus.py
vkit/engine/char_sampler/datetime.py
vkit/engine/char_sampler/faker.py
vkit/engine/char_sampler/func_collate.py
vkit/engine/char_sampler/lexicon.py
vkit/engine/char_sampler/type.py
vkit/engine/font/__init__.py
vkit/engine/font/freetype.py
vkit/engine/font/type.py
vkit/engine/image/__init__.py
vkit/engine/image/combiner.py
vkit/engine/image/selector.py
vkit/engine/image/type.py
vkit/engine/seal_impression/__init__.py
vkit/engine/seal_impression/ellipse.py
vkit/engine/seal_impression/text_line_slot_filler.py
vkit/engine/seal_impression/type.py
vkit/mechanism/__init__.py
vkit/mechanism/cropper.py
vkit/mechanism/painter.py
vkit/mechanism/distortion/__init__.py
vkit/mechanism/distortion/interface.py
vkit/mechanism/distortion/geometric/__init__.py
vkit/mechanism/distortion/geometric/affine.py
vkit/mechanism/distortion/geometric/camera.py
vkit/mechanism/distortion/geometric/mls.py
vkit/mechanism/distortion/geometric/grid_rendering/__init__.py
vkit/mechanism/distortion/geometric/grid_rendering/grid_blender.py
vkit/mechanism/distortion/geometric/grid_rendering/grid_creator.py
vkit/mechanism/distortion/geometric/grid_rendering/interface.py
vkit/mechanism/distortion/geometric/grid_rendering/point_projector.py
vkit/mechanism/distortion/geometric/grid_rendering/type.py
vkit-22.3.0.dist-info/LICENSE.txt
vkit-22.3.0.dist-info/LICENSE_COMMERCIAL.txt
vkit-22.3.0.dist-info/LICENSE_SSPL.txt
vkit-22.3.0.dist-info/METADATA
vkit-22.3.0.dist-info/WHEEL
vkit-22.3.0.dist-info/top_level.txt
vkit-22.3.0.dist-info/RECORD
